inference_schema/__init__.py
inference_schema/_constants.py
inference_schema/schema_decorators.py
inference_schema/schema_util.py
inference_schema/parameter_types/__init__.py
inference_schema/parameter_types/_constants.py
inference_schema/parameter_types/_swagger_from_dtype.py
inference_schema/parameter_types/_util.py
inference_schema/parameter_types/abstract_parameter_type.py
inference_schema/parameter_types/numpy_parameter_type.py
inference_schema/parameter_types/pandas_parameter_type.py
inference_schema/parameter_types/spark_parameter_type.py
inference_schema/parameter_types/standard_py_parameter_type.py
inference_schema-1.8.dist-info/LICENSE.txt
inference_schema-1.8.dist-info/METADATA
inference_schema-1.8.dist-info/WHEEL
inference_schema-1.8.dist-info/top_level.txt
inference_schema-1.8.dist-info/RECORD
