Metadata-Version: 2.1
Name: inference-schema
Version: 1.8
Summary: This package is intended to provide a uniform schema for common machine learning applications, as well as a set of decorators that can be used to aid in web based ML prediction applications.
Author: Microsoft Corp
License: MIT License        
Classifier: Development Status :: 3 - Alpha
Classifier: Intended Audience :: Developers
Classifier: Intended Audience :: System Administrators
Classifier: Programming Language :: Python :: 3
Classifier: Programming Language :: Python :: 3.8
Classifier: Programming Language :: Python :: 3.9
Classifier: Programming Language :: Python :: 3.10
Classifier: Programming Language :: Python :: 3.11
Classifier: Programming Language :: Python :: 3.12
Requires-Python: >=3.8
License-File: LICENSE.txt
Requires-Dist: python-dateutil (>=2.5.3)
Requires-Dist: pytz (>=2017.2)
Requires-Dist: wrapt (<=1.16.0,>=1.14.0)
Provides-Extra: numpy-support
Requires-Dist: numpy (>=1.13.0) ; extra == 'numpy-support'
Provides-Extra: pandas-support
Requires-Dist: pandas (>=0.20.2) ; extra == 'pandas-support'
Provides-Extra: pyspark-support
Requires-Dist: pyspark (>=2.3.2) ; extra == 'pyspark-support'
